[{"name":"Product Filtering &#8211; Variation 9","ID":34594,"pro":false,"liveurl":"https:\/\/wopb.wpxpo.com\/design\/product-filtering-variation-9\/","search":"","image":"https:\/\/wopb.wpxpo.com\/wp-content\/uploads\/2024\/08\/product-filtering-variation-09.jpg","hit":49,"category":[{"name":"Product Filtering","slug":"filter"}]},{"name":"Product Filtering &#8211; Variation 8","ID":34593,"pro":false,"liveurl":"https:\/\/wopb.wpxpo.com\/design\/product-filtering-variation-8\/","search":"","image":"https:\/\/wopb.wpxpo.com\/wp-content\/uploads\/2024\/08\/product-filtering-variation-08.jpg","hit":10,"category":[{"name":"Product Filtering","slug":"filter"}]},{"name":"Product Filtering &#8211; Variation 7","ID":34592,"pro":false,"liveurl":"https:\/\/wopb.wpxpo.com\/design\/product-filtering-variation-7\/","search":"","image":"https:\/\/wopb.wpxpo.com\/wp-content\/uploads\/2024\/08\/product-filtering-variation-07.jpg","hit":8,"category":[{"name":"Product Filtering","slug":"filter"}]},{"name":"Product Filtering &#8211; Variation 6","ID":34591,"pro":false,"liveurl":"https:\/\/wopb.wpxpo.com\/design\/product-filtering-variation-6\/","search":"","image":"https:\/\/wopb.wpxpo.com\/wp-content\/uploads\/2024\/08\/product-filtering-variation-06.jpg","hit":6,"category":[{"name":"Product Filtering","slug":"filter"}]},{"name":"Product Filtering &#8211; Variation 5","ID":34590,"pro":false,"liveurl":"https:\/\/wopb.wpxpo.com\/design\/product-filtering-variation-5\/","search":"","image":"https:\/\/wopb.wpxpo.com\/wp-content\/uploads\/2024\/08\/product-filtering-variation-05.jpg","hit":6,"category":[{"name":"Product Filtering","slug":"filter"}]},{"name":"Product Filtering &#8211; Variation 4","ID":34589,"pro":false,"liveurl":"https:\/\/wopb.wpxpo.com\/design\/product-filtering-variation-4\/","search":"","image":"https:\/\/wopb.wpxpo.com\/wp-content\/uploads\/2024\/08\/product-filtering-variation-04.jpg","hit":4,"category":[{"name":"Product Filtering","slug":"filter"}]},{"name":"Product Filtering &#8211; Variation 3","ID":34588,"pro":false,"liveurl":"https:\/\/wopb.wpxpo.com\/design\/product-filtering-variation-3\/","search":"","image":"https:\/\/wopb.wpxpo.com\/wp-content\/uploads\/2024\/08\/product-filtering-variation-03.jpg","hit":6,"category":[{"name":"Product Filtering","slug":"filter"}]},{"name":"Product Filtering &#8211; Variation 2","ID":34587,"pro":false,"liveurl":"https:\/\/wopb.wpxpo.com\/design\/product-filtering-variation-2\/","search":"","image":"https:\/\/wopb.wpxpo.com\/wp-content\/uploads\/2024\/08\/product-filtering-variation-02.jpg","hit":6,"category":[{"name":"Product Filtering","slug":"filter"}]},{"name":"Product Filtering &#8211; Variation 10","ID":34595,"pro":false,"liveurl":"https:\/\/wopb.wpxpo.com\/design\/product-filtering-variation-10\/","search":"","image":"https:\/\/wopb.wpxpo.com\/wp-content\/uploads\/2024\/08\/product-filtering-variation-10.jpg","hit":1,"category":[{"name":"Product Filtering","slug":"filter"}]},{"name":"Product Filtering &#8211; Default Variation","ID":34586,"pro":false,"liveurl":"https:\/\/wopb.wpxpo.com\/design\/product-filtering-default-variation\/","search":"","image":"https:\/\/wopb.wpxpo.com\/wp-content\/uploads\/2024\/08\/product-filtering-variation-01.jpg","hit":8,"category":[{"name":"Product Filtering","slug":"filter"}]},{"name":"Product List #1 \u2013 Variation 9","ID":34579,"pro":false,"liveurl":"https:\/\/wopb.wpxpo.com\/design\/product-list-1-variation-9\/","search":"","image":"https:\/\/wopb.wpxpo.com\/wp-content\/uploads\/2024\/08\/product-list-01-variation-09.png","hit":3,"category":[{"name":"Product List 1","slug":"product-list-1"}]},{"name":"Product List #1 \u2013 Variation 8","ID":34578,"pro":false,"liveurl":"https:\/\/wopb.wpxpo.com\/design\/product-list-1-variation-8\/","search":"","image":"https:\/\/wopb.wpxpo.com\/wp-content\/uploads\/2024\/08\/product-list-01-variation-08.png","hit":4,"category":[{"name":"Product List 1","slug":"product-list-1"}]},{"name":"Product List #1 \u2013 Variation 7","ID":34577,"pro":false,"liveurl":"https:\/\/wopb.wpxpo.com\/design\/product-list-1-variation-7\/","search":"","image":"https:\/\/wopb.wpxpo.com\/wp-content\/uploads\/2024\/08\/product-list-01-variation-07.png","hit":7,"category":[{"name":"Product List 1","slug":"product-list-1"}]},{"name":"Product List #1 \u2013 Variation 6","ID":34576,"pro":false,"liveurl":"https:\/\/wopb.wpxpo.com\/design\/product-list-1-variation-6\/","search":"","image":"https:\/\/wopb.wpxpo.com\/wp-content\/uploads\/2024\/08\/product-list-01-variation-06.png","hit":2,"category":[{"name":"Product List 1","slug":"product-list-1"}]},{"name":"Product List #1 \u2013 Variation 5","ID":34575,"pro":false,"liveurl":"https:\/\/wopb.wpxpo.com\/design\/product-list-1-variation-5\/","search":"","image":"https:\/\/wopb.wpxpo.com\/wp-content\/uploads\/2024\/08\/product-list-01-variation-05.png","hit":3,"category":[{"name":"Product List 1","slug":"product-list-1"}]},{"name":"Product List #1 \u2013 Variation 4","ID":34574,"pro":false,"liveurl":"https:\/\/wopb.wpxpo.com\/design\/product-list-1-variation-4\/","search":"","image":"https:\/\/wopb.wpxpo.com\/wp-content\/uploads\/2024\/08\/product-list-01-variation-04.png","hit":1,"category":[{"name":"Product List 1","slug":"product-list-1"}]},{"name":"Product List #1 \u2013 Variation 3","ID":34573,"pro":false,"liveurl":"https:\/\/wopb.wpxpo.com\/design\/product-list-1-variation-3\/","search":"","image":"https:\/\/wopb.wpxpo.com\/wp-content\/uploads\/2024\/08\/product-list-01-variation-03.png","hit":3,"category":[{"name":"Product List 1","slug":"product-list-1"}]},{"name":"Product List #1 \u2013 Variation 2","ID":34572,"pro":false,"liveurl":"https:\/\/wopb.wpxpo.com\/design\/product-list-1-variation-2\/","search":"","image":"https:\/\/wopb.wpxpo.com\/wp-content\/uploads\/2024\/08\/product-list-01-variation-02.png","hit":13,"category":[{"name":"Product List 1","slug":"product-list-1"}]},{"name":"Product List #1 \u2013 Variation 10","ID":34580,"pro":false,"liveurl":"https:\/\/wopb.wpxpo.com\/design\/product-list-1-variation-10\/","search":"","image":"https:\/\/wopb.wpxpo.com\/wp-content\/uploads\/2024\/08\/product-list-01-variation-10.png","hit":6,"category":[{"name":"Product List 1","slug":"product-list-1"}]},{"name":"Product List #1 \u2013 Default Variation","ID":34571,"pro":false,"liveurl":"https:\/\/wopb.wpxpo.com\/design\/product-list-1-default-variation\/","search":"","image":"https:\/\/wopb.wpxpo.com\/wp-content\/uploads\/2024\/08\/product-list-01-variation-01.png","hit":5,"category":[{"name":"Product List 1","slug":"product-list-1"}]},{"name":"Product Category 3 \u2013 Variation 9","ID":34569,"pro":false,"liveurl":"https:\/\/wopb.wpxpo.com\/design\/product-category-3-variation-9\/","search":"","image":"https:\/\/wopb.wpxpo.com\/wp-content\/uploads\/2024\/08\/product-categories-03-variation-09.png","hit":7,"category":[{"name":"Product Category 3","slug":"product-category-3"}]},{"name":"Product Category 3 \u2013 Variation 8","ID":34568,"pro":false,"liveurl":"https:\/\/wopb.wpxpo.com\/design\/product-category-3-variation-8\/","search":"","image":"https:\/\/wopb.wpxpo.com\/wp-content\/uploads\/2024\/08\/product-categories-03-variation-08.png","hit":8,"category":[{"name":"Product Category 3","slug":"product-category-3"}]},{"name":"Product Category 3 \u2013 Variation 7","ID":34567,"pro":false,"liveurl":"https:\/\/wopb.wpxpo.com\/design\/product-category-3-variation-7\/","search":"","image":"https:\/\/wopb.wpxpo.com\/wp-content\/uploads\/2024\/08\/product-categories-03-variation-07.png","hit":7,"category":[{"name":"Product Category 3","slug":"product-category-3"}]},{"name":"Product Category 3 \u2013 Variation 6","ID":34566,"pro":false,"liveurl":"https:\/\/wopb.wpxpo.com\/design\/product-category-3-variation-6\/","search":"","image":"https:\/\/wopb.wpxpo.com\/wp-content\/uploads\/2024\/08\/product-categories-03-variation-06.png","hit":2,"category":[{"name":"Product Category 3","slug":"product-category-3"}]},{"name":"Product Category 3 \u2013 Variation 5","ID":34565,"pro":false,"liveurl":"https:\/\/wopb.wpxpo.com\/design\/product-category-3-variation-5\/","search":"","image":"https:\/\/wopb.wpxpo.com\/wp-content\/uploads\/2024\/08\/product-categories-03-variation-05.png","hit":1,"category":[{"name":"Product Category 3","slug":"product-category-3"}]},{"name":"Product Category 3 \u2013 Variation 4","ID":34563,"pro":false,"liveurl":"https:\/\/wopb.wpxpo.com\/design\/product-category-3-variation-4\/","search":"","image":"https:\/\/wopb.wpxpo.com\/wp-content\/uploads\/2024\/08\/product-categories-03-variation-04.png","hit":1,"category":[{"name":"Product Category 3","slug":"product-category-3"}]},{"name":"Product Category 3 \u2013 Variation 3","ID":34562,"pro":false,"liveurl":"https:\/\/wopb.wpxpo.com\/design\/product-category-3-variation-3\/","search":"","image":"https:\/\/wopb.wpxpo.com\/wp-content\/uploads\/2024\/08\/product-categories-03-variation-03.png","hit":8,"category":[{"name":"Product Category 3","slug":"product-category-3"}]},{"name":"Product Category 3 \u2013 Variation 2","ID":34561,"pro":false,"liveurl":"https:\/\/wopb.wpxpo.com\/design\/product-category-3-variation-2\/","search":"","image":"https:\/\/wopb.wpxpo.com\/wp-content\/uploads\/2024\/08\/product-categories-03-variation-02.png","hit":1,"category":[{"name":"Product Category 3","slug":"product-category-3"}]},{"name":"Product Category 3 \u2013 Variation 10","ID":34570,"pro":false,"liveurl":"https:\/\/wopb.wpxpo.com\/design\/product-category-3-variation-10\/","search":"","image":"https:\/\/wopb.wpxpo.com\/wp-content\/uploads\/2024\/08\/product-categories-03-variation-10.png","hit":16,"category":[{"name":"Product Category 3","slug":"product-category-3"}]},{"name":"Product Category 3 \u2013 Default Variation","ID":34560,"pro":false,"liveurl":"https:\/\/wopb.wpxpo.com\/design\/product-category-3-default-variation\/","search":"","image":"https:\/\/wopb.wpxpo.com\/wp-content\/uploads\/2024\/08\/product-categories-03-variation-01.png","hit":1,"category":[{"name":"Product Category 3","slug":"product-category-3"}]},{"name":"Product Category 2 \u2013 Variation 9","ID":34558,"pro":false,"liveurl":"https:\/\/wopb.wpxpo.com\/design\/product-category-2-variation-9\/","search":"","image":"https:\/\/wopb.wpxpo.com\/wp-content\/uploads\/2024\/08\/product-categories-02-variation-09.png","hit":4,"category":[{"name":"Product Category 2","slug":"product-category-2"}]},{"name":"Product Category 2 \u2013 Variation 7","ID":34556,"pro":false,"liveurl":"Product Category 2 \u2013 Variation 1","search":"","image":"https:\/\/wopb.wpxpo.com\/wp-content\/uploads\/2024\/08\/product-categories-02-variation-07.png","hit":4,"category":[{"name":"Product Category 2","slug":"product-category-2"}]},{"name":"Product Category 2 \u2013 Variation 8","ID":34557,"pro":false,"liveurl":"https:\/\/wopb.wpxpo.com\/design\/product-category-2-variation-8\/","search":"","image":"https:\/\/wopb.wpxpo.com\/wp-content\/uploads\/2024\/08\/product-categories-02-variation-08.png","hit":6,"category":[{"name":"Product Category 2","slug":"product-category-2"}]},{"name":"Product Category 2 \u2013 Variation 5","ID":34554,"pro":false,"liveurl":"https:\/\/wopb.wpxpo.com\/design\/product-category-2-variation-5\/","search":"","image":"https:\/\/wopb.wpxpo.com\/wp-content\/uploads\/2024\/08\/product-categories-02-variation-05.png","hit":3,"category":[{"name":"Product Category 2","slug":"product-category-2"}]},{"name":"Product Category 2 \u2013 Variation 4","ID":34553,"pro":false,"liveurl":"https:\/\/wopb.wpxpo.com\/design\/product-category-2-variation-4\/","search":"","image":"https:\/\/wopb.wpxpo.com\/wp-content\/uploads\/2024\/08\/product-categories-02-variation-04.png","hit":2,"category":[{"name":"Product Category 2","slug":"product-category-2"}]},{"name":"Product Category 2 \u2013 Variation 3","ID":34552,"pro":false,"liveurl":"https:\/\/wopb.wpxpo.com\/design\/product-category-2-variation-3\/","search":"","image":"https:\/\/wopb.wpxpo.com\/wp-content\/uploads\/2024\/08\/product-categories-02-variation-03.png","hit":2,"category":[{"name":"Product Category 2","slug":"product-category-2"}]},{"name":"Product Category 2 \u2013 Variation 2","ID":34551,"pro":false,"liveurl":"https:\/\/wopb.wpxpo.com\/design\/product-category-2-variation-2\/","search":"","image":"https:\/\/wopb.wpxpo.com\/wp-content\/uploads\/2024\/08\/product-categories-02-variation-02.png","hit":2,"category":[{"name":"Product Category 2","slug":"product-category-2"}]},{"name":"Product Category 2 \u2013 Variation 10","ID":34559,"pro":false,"liveurl":"https:\/\/wopb.wpxpo.com\/design\/product-category-2-variation-10\/","search":"","image":"https:\/\/wopb.wpxpo.com\/wp-content\/uploads\/2024\/08\/product-categories-02-variation-10.png","hit":4,"category":[{"name":"Product Category 2","slug":"product-category-2"}]},{"name":"Product Category 2 \u2013 Default Variation","ID":34550,"pro":false,"liveurl":"https:\/\/wopb.wpxpo.com\/design\/product-category-2-default-variation\/","search":"","image":"https:\/\/wopb.wpxpo.com\/wp-content\/uploads\/2024\/08\/product-categories-02-variation-01.png","hit":0,"category":[{"name":"Product Category 2","slug":"product-category-2"}]},{"name":"Product Category 1 \u2013 Variation 9","ID":34548,"pro":false,"liveurl":"https:\/\/wopb.wpxpo.com\/design\/product-category-1-variation-9\/","search":"","image":"https:\/\/wopb.wpxpo.com\/wp-content\/uploads\/2024\/08\/product-categories-01-variation-09.png","hit":8,"category":[{"name":"Product Category 1","slug":"product-category-1"}]},{"name":"Product Category 1 \u2013 Variation 8","ID":34547,"pro":false,"liveurl":"https:\/\/wopb.wpxpo.com\/design\/product-category-1-variation-8\/","search":"","image":"https:\/\/wopb.wpxpo.com\/wp-content\/uploads\/2024\/08\/product-categories-01-variation-08.png","hit":7,"category":[{"name":"Product Category 1","slug":"product-category-1"}]},{"name":"Product Category 1 \u2013 Variation 7","ID":34546,"pro":false,"liveurl":"https:\/\/wopb.wpxpo.com\/design\/product-category-1-variation-7\/","search":"","image":"https:\/\/wopb.wpxpo.com\/wp-content\/uploads\/2024\/08\/product-categories-01-variation-07.png","hit":12,"category":[{"name":"Product Category 1","slug":"product-category-1"}]},{"name":"Product Category 1 \u2013 Variation 6","ID":34545,"pro":false,"liveurl":"https:\/\/wopb.wpxpo.com\/design\/product-category-1-variation-6\/","search":"","image":"https:\/\/wopb.wpxpo.com\/wp-content\/uploads\/2024\/08\/product-categories-01-variation-06.png","hit":4,"category":[{"name":"Product Category 1","slug":"product-category-1"}]},{"name":"Product Category 1 \u2013 Variation 4","ID":34543,"pro":false,"liveurl":"https:\/\/wopb.wpxpo.com\/design\/product-category-1-variation-4\/","search":"","image":"https:\/\/wopb.wpxpo.com\/wp-content\/uploads\/2024\/08\/product-categories-01-variation-04.png","hit":9,"category":[{"name":"Product Category 1","slug":"product-category-1"}]},{"name":"Product Category 1 \u2013 Variation 5","ID":34544,"pro":false,"liveurl":"https:\/\/wopb.wpxpo.com\/design\/product-category-1-variation-5\/","search":"","image":"https:\/\/wopb.wpxpo.com\/wp-content\/uploads\/2024\/08\/product-categories-01-variation-05.png","hit":4,"category":[{"name":"Product Category 1","slug":"product-category-1"}]},{"name":"Product Category 1 \u2013 Variation 2","ID":34541,"pro":false,"liveurl":"https:\/\/wopb.wpxpo.com\/design\/product-category-1-variation-2\/","search":"","image":"https:\/\/wopb.wpxpo.com\/wp-content\/uploads\/2024\/08\/product-categories-01-variation-02.png","hit":0,"category":[{"name":"Product Category 1","slug":"product-category-1"}]},{"name":"Product Category 1 \u2013 Variation 10","ID":34549,"pro":false,"liveurl":"https:\/\/wopb.wpxpo.com\/design\/product-category-1-variation-10\/","search":"","image":"https:\/\/wopb.wpxpo.com\/wp-content\/uploads\/2024\/08\/product-categories-01-variation-10.png","hit":5,"category":[{"name":"Product Category 1","slug":"product-category-1"}]},{"name":"Product Category 1 \u2013 Default Variation","ID":34539,"pro":false,"liveurl":"https:\/\/wopb.wpxpo.com\/design\/product-category-1-default-variation\/","search":"","image":"https:\/\/wopb.wpxpo.com\/wp-content\/uploads\/2024\/08\/product-categories-01-variation-01-1.png","hit":8,"category":[{"name":"Product Category 1","slug":"product-category-1"}]},{"name":"Product Category 1 \u2013 Variation 3","ID":34542,"pro":false,"liveurl":"https:\/\/wopb.wpxpo.com\/design\/product-category-1-variation-3\/","search":"","image":"https:\/\/wopb.wpxpo.com\/wp-content\/uploads\/2024\/08\/product-categories-01-variation-03.png","hit":4,"category":[{"name":"Product Category 1","slug":"product-category-1"}]},{"name":"Product Category 2 \u2013 Variation 6","ID":34555,"pro":false,"liveurl":"https:\/\/wopb.wpxpo.com\/design\/product-category-2-variation-6\/","search":"","image":"https:\/\/wopb.wpxpo.com\/wp-content\/uploads\/2024\/08\/product-categories-02-variation-06.png","hit":10,"category":[{"name":"Product Category 2","slug":"product-category-2"}]},{"name":"Product Grid #2 \u2013 Variation 10","ID":34325,"pro":false,"liveurl":"https:\/\/wopb.wpxpo.com\/design\/product-grid-2-variation-10\/","search":"","image":"https:\/\/wopb.wpxpo.com\/wp-content\/uploads\/2024\/07\/Product_Grid_2_Variation_10.jpg","hit":56,"category":[{"name":"Product Grid 2","slug":"product-grid-2"}]},{"name":"Product Grid #2 \u2013 Variation 9","ID":34328,"pro":false,"liveurl":"https:\/\/wopb.wpxpo.com\/design\/product-grid-2-variation-9\/","search":"","image":"https:\/\/wopb.wpxpo.com\/wp-content\/uploads\/2024\/07\/Product_Grid_2_Variation_09.jpg","hit":26,"category":[{"name":"Product Grid 2","slug":"product-grid-2"}]},{"name":"Product Grid #2 \u2013 Variation 8","ID":34324,"pro":false,"liveurl":"https:\/\/wopb.wpxpo.com\/design\/product-grid-2-variation-8\/","search":"","image":"https:\/\/wopb.wpxpo.com\/wp-content\/uploads\/2024\/07\/Product_Grid_2_Variation_08.jpg","hit":15,"category":[{"name":"Product Grid 2","slug":"product-grid-2"}]},{"name":"Product Grid #2 \u2013 Variation 7","ID":34323,"pro":false,"liveurl":"https:\/\/wopb.wpxpo.com\/design\/product-grid-2-variation-7\/","search":"","image":"https:\/\/wopb.wpxpo.com\/wp-content\/uploads\/2024\/07\/Product_Grid_2_Variation_07.jpg","hit":19,"category":[{"name":"Product Grid 2","slug":"product-grid-2"}]},{"name":"Product Grid #2 \u2013 Variation 6","ID":34322,"pro":false,"liveurl":"https:\/\/wopb.wpxpo.com\/design\/product-grid-2-variation-6\/","search":"","image":"https:\/\/wopb.wpxpo.com\/wp-content\/uploads\/2024\/07\/Product_Grid_2_Variation_06.jpg","hit":16,"category":[{"name":"Product Grid 2","slug":"product-grid-2"}]},{"name":"Product Grid #2 \u2013 Variation 5","ID":34321,"pro":false,"liveurl":"https:\/\/wopb.wpxpo.com\/design\/product-grid-2-variation-5\/","search":"","image":"https:\/\/wopb.wpxpo.com\/wp-content\/uploads\/2024\/07\/Product_Grid_2_Variation_05.jpg","hit":17,"category":[{"name":"Product Grid 2","slug":"product-grid-2"}]},{"name":"Product Grid #2 \u2013 Variation 4","ID":34332,"pro":false,"liveurl":"https:\/\/wopb.wpxpo.com\/design\/product-grid-2-variation-4\/","search":"","image":"https:\/\/wopb.wpxpo.com\/wp-content\/uploads\/2024\/07\/Product_Grid_2_Variation_04.jpg","hit":16,"category":[{"name":"Product Grid 2","slug":"product-grid-2"}]},{"name":"Product Grid #2 \u2013 Variation 3","ID":34331,"pro":false,"liveurl":"https:\/\/wopb.wpxpo.com\/design\/product-grid-2-variation-3\/","search":"","image":"https:\/\/wopb.wpxpo.com\/wp-content\/uploads\/2024\/09\/Product_Grid_2_Variation_03_Corrected.jpg","hit":7,"category":[{"name":"Product Grid 2","slug":"product-grid-2"}]},{"name":"Product Grid #2 \u2013 Variation 2","ID":34330,"pro":false,"liveurl":"https:\/\/wopb.wpxpo.com\/design\/product-grid-2-variation-2\/","search":"","image":"https:\/\/wopb.wpxpo.com\/wp-content\/uploads\/2024\/09\/Product_Grid_2_Variation_02_Corrected.jpg","hit":10,"category":[{"name":"Product Grid 2","slug":"product-grid-2"}]},{"name":"Product Grid #2 \u2013 Default Variation","ID":34329,"pro":false,"liveurl":"https:\/\/wopb.wpxpo.com\/design\/product-grid-2-default-variation\/","search":"","image":"https:\/\/wopb.wpxpo.com\/wp-content\/uploads\/2024\/07\/Product_Grid_2_Variation_01.jpg","hit":22,"category":[{"name":"Product Grid 2","slug":"product-grid-2"}]},{"name":"Product Grid #3 \u2013 Variation 10","ID":34235,"pro":false,"liveurl":"https:\/\/wopb.wpxpo.com\/design\/product-grid-3-variation-10\/","search":"","image":"https:\/\/wopb.wpxpo.com\/wp-content\/uploads\/2024\/07\/Product_Grid_3_Variation_10.jpg","hit":34,"category":[{"name":"Product Grid 3","slug":"product-grid-3"}]},{"name":"Product Grid #3 \u2013 Variation 9","ID":34234,"pro":false,"liveurl":"https:\/\/wopb.wpxpo.com\/design\/product-grid-3-variation-9\/","search":"","image":"https:\/\/wopb.wpxpo.com\/wp-content\/uploads\/2024\/07\/Product_Grid_3_Variation_09.jpg","hit":27,"category":[{"name":"Product Grid 3","slug":"product-grid-3"}]},{"name":"Product Grid #3 \u2013 Variation 8","ID":34233,"pro":false,"liveurl":"https:\/\/wopb.wpxpo.com\/design\/product-grid-3-variation-8\/","search":"","image":"https:\/\/wopb.wpxpo.com\/wp-content\/uploads\/2024\/07\/Product_Grid_3_Variation_08.jpg","hit":12,"category":[{"name":"Product Grid 3","slug":"product-grid-3"}]},{"name":"Product Grid #1 &#8211; Variation 10","ID":34299,"pro":false,"liveurl":"https:\/\/wopb.wpxpo.com\/design\/variation-10\/","search":"","image":"https:\/\/wopb.wpxpo.com\/wp-content\/uploads\/2024\/07\/Product-Grid-1-Variation-10.jpg","hit":34,"category":[{"name":"Product Grid 1","slug":"product-grid-1"}]},{"name":"Product Grid #3 \u2013 Variation 7","ID":34232,"pro":false,"liveurl":"https:\/\/wopb.wpxpo.com\/design\/product-grid-3-variation-7\/","search":"","image":"https:\/\/wopb.wpxpo.com\/wp-content\/uploads\/2024\/07\/Product_Grid_3_Variation_07.jpg","hit":17,"category":[{"name":"Product Grid 3","slug":"product-grid-3"}]},{"name":"Product Grid #3 \u2013 Variation 6","ID":34231,"pro":false,"liveurl":"https:\/\/wopb.wpxpo.com\/design\/product-grid-3-variation-6\/","search":"","image":"https:\/\/wopb.wpxpo.com\/wp-content\/uploads\/2024\/07\/Product_Grid_3_Variation_06.jpg","hit":15,"category":[{"name":"Product Grid 3","slug":"product-grid-3"}]},{"name":"Product Grid #3 \u2013 Variation 5","ID":34230,"pro":false,"liveurl":"https:\/\/wopb.wpxpo.com\/design\/product-grid-3-variation-5\/","search":"","image":"https:\/\/wopb.wpxpo.com\/wp-content\/uploads\/2024\/07\/Product_Grid_3_Variation_05.jpg","hit":11,"category":[{"name":"Product Grid 3","slug":"product-grid-3"}]},{"name":"Product Grid #1 &#8211; Variation 9","ID":34288,"pro":false,"liveurl":"","search":"","image":"https:\/\/wopb.wpxpo.com\/wp-content\/uploads\/2024\/07\/Product-Grid-1-Variation-09.jpg","hit":25,"category":[{"name":"Product Grid 1","slug":"product-grid-1"}]},{"name":"Product Grid #1 &#8211; Variation 8","ID":34274,"pro":false,"liveurl":"https:\/\/wopb.wpxpo.com\/design\/variation-8\/","search":"","image":"https:\/\/wopb.wpxpo.com\/wp-content\/uploads\/2024\/07\/Product-Grid-1-Variation-08.jpg","hit":45,"category":[{"name":"Product Grid 1","slug":"product-grid-1"}]},{"name":"Product Grid #3 \u2013 Variation 4","ID":34229,"pro":false,"liveurl":"https:\/\/wopb.wpxpo.com\/design\/product-grid-3-variation-4\/","search":"","image":"https:\/\/wopb.wpxpo.com\/wp-content\/uploads\/2024\/07\/Product_Grid_3_Variation_04.jpg","hit":12,"category":[{"name":"Product Grid 3","slug":"product-grid-3"}]},{"name":"Product Grid #3 \u2013 Variation 3","ID":34228,"pro":false,"liveurl":"https:\/\/wopb.wpxpo.com\/design\/product-grid-3-variation-3\/","search":"","image":"https:\/\/wopb.wpxpo.com\/wp-content\/uploads\/2024\/07\/Product_Grid_3_Variation_03.jpg","hit":8,"category":[{"name":"Product Grid 3","slug":"product-grid-3"}]},{"name":"Product Grid #1 &#8211; Variation 7","ID":34264,"pro":false,"liveurl":"https:\/\/wopb.wpxpo.com\/design\/variation-7\/","search":"","image":"https:\/\/wopb.wpxpo.com\/wp-content\/uploads\/2024\/07\/Product-Grid-1-Variation-07.jpg","hit":25,"category":[{"name":"Product Grid 1","slug":"product-grid-1"}]},{"name":"Product Grid #3 \u2013 Variation 2","ID":34227,"pro":false,"liveurl":"https:\/\/wopb.wpxpo.com\/design\/product-grid-3-variation-2\/","search":"","image":"https:\/\/wopb.wpxpo.com\/wp-content\/uploads\/2024\/07\/Product_Grid_3_Variation_02.jpg","hit":18,"category":[{"name":"Product Grid 3","slug":"product-grid-3"}]},{"name":"Product Grid #1 &#8211; Variation 6","ID":34253,"pro":false,"liveurl":"https:\/\/wopb.wpxpo.com\/?post_type=design&p=34253","search":"","image":"https:\/\/wopb.wpxpo.com\/wp-content\/uploads\/2024\/07\/Product-Grid-1-Variation-06.jpg","hit":25,"category":[{"name":"Product Grid 1","slug":"product-grid-1"}]},{"name":"Product Grid #3 \u2013 Default Variation","ID":34223,"pro":false,"liveurl":"https:\/\/wopb.wpxpo.com\/design\/product-grid-3-default-variation\/","search":"","image":"https:\/\/wopb.wpxpo.com\/wp-content\/uploads\/2024\/07\/Product_Grid_3_Variation_01.jpg","hit":14,"category":[{"name":"Product Grid 3","slug":"product-grid-3"}]},{"name":"Banner #style 23","ID":2772,"pro":false,"liveurl":"https:\/\/wopb.wpxpo.com\/design\/banner-style-22\/","search":"","image":"https:\/\/wopb.wpxpo.com\/wp-content\/uploads\/2023\/10\/banner-23.jpg","hit":72,"category":[{"name":"Banner Maker","slug":"banner"}]},{"name":"Banner #style 22","ID":2770,"pro":false,"liveurl":"https:\/\/wopb.wpxpo.com\/design\/banner-style-22\/","search":"","image":"https:\/\/wopb.wpxpo.com\/wp-content\/uploads\/2023\/10\/banner-22.jpg","hit":62,"category":[{"name":"Banner Maker","slug":"banner"}]},{"name":"Banner #style 20","ID":2768,"pro":false,"liveurl":"https:\/\/wopb.wpxpo.com\/design\/banner-style-20\/","search":"","image":"https:\/\/wopb.wpxpo.com\/wp-content\/uploads\/2023\/10\/banner-20.jpg","hit":65,"category":[{"name":"Banner Maker","slug":"banner"}]},{"name":"Banner #style 18","ID":2763,"pro":false,"liveurl":"https:\/\/wopb.wpxpo.com\/design\/banner-style-18\/","search":"","image":"https:\/\/wopb.wpxpo.com\/wp-content\/uploads\/2023\/10\/banner-18.png","hit":35,"category":[{"name":"Banner Maker","slug":"banner"}]},{"name":"Banner #style 21","ID":2765,"pro":false,"liveurl":"https:\/\/wopb.wpxpo.com\/design\/banner-style-21\/","search":"","image":"https:\/\/wopb.wpxpo.com\/wp-content\/uploads\/2023\/10\/banner-21.jpg","hit":21,"category":[{"name":"Banner Maker","slug":"banner"}]},{"name":"Banner #style 19","ID":2750,"pro":false,"liveurl":"https:\/\/wopb.wpxpo.com\/design\/banner-style-19\/","search":"","image":"https:\/\/wopb.wpxpo.com\/wp-content\/uploads\/2023\/10\/banner-19.jpg","hit":17,"category":[{"name":"Banner Maker","slug":"banner"}]},{"name":"Banner #style 9","ID":2391,"pro":false,"liveurl":"https:\/\/wopb.wpxpo.com\/design\/banner-style-9\/","search":"","image":"https:\/\/wopb.wpxpo.com\/wp-content\/uploads\/2023\/09\/Group-22.png","hit":21,"category":[{"name":"Banner Maker","slug":"banner"}]},{"name":"Banner #style 8","ID":2390,"pro":false,"liveurl":"https:\/\/wopb.wpxpo.com\/design\/banner-style-8\/","search":"","image":"https:\/\/wopb.wpxpo.com\/wp-content\/uploads\/2023\/09\/Group-42.png","hit":141,"category":[{"name":"Banner Maker","slug":"banner"}]},{"name":"Banner #style 7","ID":2389,"pro":false,"liveurl":"https:\/\/wopb.wpxpo.com\/design\/banner-style-7\/","search":"","image":"https:\/\/wopb.wpxpo.com\/wp-content\/uploads\/2023\/09\/Group-21.png","hit":52,"category":[{"name":"Banner Maker","slug":"banner"}]},{"name":"Banner #style 6","ID":2388,"pro":false,"liveurl":"","search":"","image":"https:\/\/wopb.wpxpo.com\/wp-content\/uploads\/2023\/09\/Group-17.png","hit":54,"category":[{"name":"Banner Maker","slug":"banner"}]},{"name":"Banner #style 5","ID":2387,"pro":false,"liveurl":"https:\/\/wopb.wpxpo.com\/design\/banner-style-5\/","search":"","image":"https:\/\/wopb.wpxpo.com\/wp-content\/uploads\/2023\/09\/Group-12.png","hit":26,"category":[{"name":"Banner Maker","slug":"banner"}]},{"name":"Banner #style 4","ID":2386,"pro":false,"liveurl":"https:\/\/wopb.wpxpo.com\/design\/banner-style-4\/","search":"","image":"https:\/\/wopb.wpxpo.com\/wp-content\/uploads\/2023\/09\/Group-11.png","hit":20,"category":[{"name":"Banner Maker","slug":"banner"}]},{"name":"Banner #style 3","ID":2385,"pro":false,"liveurl":"https:\/\/wopb.wpxpo.com\/design\/banner-style-3\/","search":"","image":"https:\/\/wopb.wpxpo.com\/wp-content\/uploads\/2023\/09\/Group-9.png","hit":84,"category":[{"name":"Banner Maker","slug":"banner"}]},{"name":"Banner #style 2","ID":2384,"pro":false,"liveurl":"https:\/\/wopb.wpxpo.com\/design\/banner-style-2\/","search":"","image":"https:\/\/wopb.wpxpo.com\/wp-content\/uploads\/2023\/09\/Group-10.png","hit":39,"category":[{"name":"Banner Maker","slug":"banner"}]},{"name":"Banner #style 17","ID":2399,"pro":false,"liveurl":"https:\/\/wopb.wpxpo.com\/design\/banner-style-17\/","search":"","image":"https:\/\/wopb.wpxpo.com\/wp-content\/uploads\/2023\/09\/Group-36.png","hit":41,"category":[{"name":"Banner Maker","slug":"banner"}]},{"name":"Banner #style 16","ID":2398,"pro":false,"liveurl":"https:\/\/wopb.wpxpo.com\/design\/banner-style-16\/","search":"","image":"https:\/\/wopb.wpxpo.com\/wp-content\/uploads\/2023\/09\/Group-41.png","hit":89,"category":[{"name":"Banner Maker","slug":"banner"}]},{"name":"Banner #style 15","ID":2397,"pro":false,"liveurl":"https:\/\/wopb.wpxpo.com\/design\/banner-style-15\/","search":"","image":"https:\/\/wopb.wpxpo.com\/wp-content\/uploads\/2023\/09\/Group-2197.png","hit":87,"category":[{"name":"Banner Maker","slug":"banner"}]},{"name":"Banner #style 14","ID":2396,"pro":false,"liveurl":"https:\/\/wopb.wpxpo.com\/design\/banner-style-14\/","search":"","image":"https:\/\/wopb.wpxpo.com\/wp-content\/uploads\/2023\/09\/Group-45.png","hit":51,"category":[{"name":"Banner Maker","slug":"banner"}]},{"name":"Banner #style 13","ID":2395,"pro":false,"liveurl":"https:\/\/wopb.wpxpo.com\/design\/banner-style-13\/","search":"","image":"https:\/\/wopb.wpxpo.com\/wp-content\/uploads\/2023\/09\/Group-33.png","hit":41,"category":[{"name":"Banner Maker","slug":"banner"}]},{"name":"Banner #style 12","ID":2394,"pro":false,"liveurl":"https:\/\/wopb.wpxpo.com\/design\/banner-style-12\/","search":"","image":"https:\/\/wopb.wpxpo.com\/wp-content\/uploads\/2023\/09\/Group-2196.png","hit":63,"category":[{"name":"Banner Maker","slug":"banner"}]},{"name":"Banner #style 11","ID":2393,"pro":false,"liveurl":"https:\/\/wopb.wpxpo.com\/design\/banner-style-11\/","search":"","image":"https:\/\/wopb.wpxpo.com\/wp-content\/uploads\/2023\/09\/Group-26.png","hit":44,"category":[{"name":"Banner Maker","slug":"banner"}]},{"name":"Banner #style 10","ID":2392,"pro":false,"liveurl":"","search":"","image":"https:\/\/wopb.wpxpo.com\/wp-content\/uploads\/2023\/09\/Group-2179.png","hit":60,"category":[{"name":"Banner Maker","slug":"banner"}]},{"name":"Banner #style 1","ID":2372,"pro":false,"liveurl":"https:\/\/wopb.wpxpo.com\/design\/banner-style-1\/","search":"","image":"https:\/\/wopb.wpxpo.com\/wp-content\/uploads\/2023\/09\/Group-2293.png","hit":131,"category":[{"name":"Banner Maker","slug":"banner"}]},{"name":"List-ProductX Style 11","ID":2143,"pro":false,"liveurl":"https:\/\/wopb.wpxpo.com\/design\/list-productx-style-11\/","search":"","image":"https:\/\/wopb.wpxpo.com\/wp-content\/uploads\/2023\/08\/advance-list-11.jpg","hit":23,"category":[{"name":"advance-list","slug":"advance-list"}]},{"name":"List-ProductX Style 10","ID":2142,"pro":false,"liveurl":"https:\/\/wopb.wpxpo.com\/design\/list-productx-style-10\/","search":"","image":"https:\/\/wopb.wpxpo.com\/wp-content\/uploads\/2023\/08\/advance-list-10.jpg","hit":6,"category":[{"name":"advance-list","slug":"advance-list"}]},{"name":"List-ProductX Style 9","ID":2141,"pro":false,"liveurl":"https:\/\/wopb.wpxpo.com\/design\/list-productx-style-9\/","search":"","image":"https:\/\/wopb.wpxpo.com\/wp-content\/uploads\/2023\/08\/advance-list-9.jpg","hit":51,"category":[{"name":"advance-list","slug":"advance-list"}]},{"name":"List-ProductX Style 8","ID":2140,"pro":false,"liveurl":"https:\/\/wopb.wpxpo.com\/design\/list-productx-style-8\/","search":"","image":"https:\/\/wopb.wpxpo.com\/wp-content\/uploads\/2023\/08\/advance-list-8.jpg","hit":16,"category":[{"name":"advance-list","slug":"advance-list"}]},{"name":"List-ProductX Style 7","ID":2139,"pro":false,"liveurl":"https:\/\/wopb.wpxpo.com\/design\/list-productx-style-7\/","search":"","image":"https:\/\/wopb.wpxpo.com\/wp-content\/uploads\/2023\/08\/advance-list-7.jpg","hit":44,"category":[{"name":"advance-list","slug":"advance-list"}]},{"name":"List-ProductX Style 6","ID":2138,"pro":false,"liveurl":"https:\/\/wopb.wpxpo.com\/design\/list-productx-style-6\/","search":"","image":"https:\/\/wopb.wpxpo.com\/wp-content\/uploads\/2023\/08\/advance-list-6.jpg","hit":7,"category":[{"name":"advance-list","slug":"advance-list"}]},{"name":"List-ProductX Style 5","ID":2137,"pro":false,"liveurl":"","search":"","image":"https:\/\/wopb.wpxpo.com\/wp-content\/uploads\/2023\/08\/advance-list-5.jpg","hit":23,"category":[{"name":"advance-list","slug":"advance-list"}]},{"name":"List-ProductX Style 4","ID":2136,"pro":false,"liveurl":"https:\/\/wopb.wpxpo.com\/design\/list-productx-style-4\/","search":"","image":"https:\/\/wopb.wpxpo.com\/wp-content\/uploads\/2023\/08\/advance-list-4.jpg","hit":5,"category":[{"name":"advance-list","slug":"advance-list"}]},{"name":"List-ProductX Style 3","ID":2135,"pro":false,"liveurl":"https:\/\/wopb.wpxpo.com\/design\/list-productx-style-3\/","search":"","image":"https:\/\/wopb.wpxpo.com\/wp-content\/uploads\/2023\/08\/advance-list-3.jpg","hit":44,"category":[{"name":"advance-list","slug":"advance-list"}]},{"name":"List-ProductX Style 2","ID":2134,"pro":false,"liveurl":"https:\/\/wopb.wpxpo.com\/design\/list-productx-style-2\/","search":"","image":"https:\/\/wopb.wpxpo.com\/wp-content\/uploads\/2023\/08\/advance-list-2.jpg","hit":43,"category":[{"name":"advance-list","slug":"advance-list"}]},{"name":"List-ProductX Style 1","ID":2132,"pro":false,"liveurl":"https:\/\/wopb.wpxpo.com\/design\/list-productx-style-1\/","search":"","image":"https:\/\/wopb.wpxpo.com\/wp-content\/uploads\/2023\/08\/advance-list-1.jpg","hit":28,"category":[{"name":"advance-list","slug":"advance-list"}]},{"name":"Button #style 6","ID":2102,"pro":false,"liveurl":"https:\/\/wopb.wpxpo.com\/design\/button-group-style-6\/","search":"","image":"https:\/\/wopb.wpxpo.com\/wp-content\/uploads\/2023\/08\/Button-6.jpg","hit":38,"category":[{"name":"Button Group","slug":"button-group"}]},{"name":"Button #style 5","ID":2101,"pro":false,"liveurl":"https:\/\/wopb.wpxpo.com\/design\/button-group-style-5\/","search":"","image":"https:\/\/wopb.wpxpo.com\/wp-content\/uploads\/2023\/08\/Button-5.jpg","hit":30,"category":[{"name":"Button Group","slug":"button-group"}]},{"name":"Button #style 4","ID":2100,"pro":false,"liveurl":"https:\/\/wopb.wpxpo.com\/design\/button-group-style-4\/","search":"","image":"https:\/\/wopb.wpxpo.com\/wp-content\/uploads\/2023\/08\/Button-4.jpg","hit":63,"category":[{"name":"Button Group","slug":"button-group"}]},{"name":"Button #style 3","ID":2099,"pro":false,"liveurl":"https:\/\/wopb.wpxpo.com\/design\/button-group-style-3\/","search":"","image":"https:\/\/wopb.wpxpo.com\/wp-content\/uploads\/2023\/08\/Button-3.jpg","hit":50,"category":[{"name":"Button Group","slug":"button-group"}]},{"name":"Button #style 2","ID":2098,"pro":false,"liveurl":"https:\/\/wopb.wpxpo.com\/design\/button-group-style-2\/","search":"","image":"https:\/\/wopb.wpxpo.com\/wp-content\/uploads\/2023\/08\/Button-2.jpg","hit":63,"category":[{"name":"Button Group","slug":"button-group"}]},{"name":"Button #style 1","ID":2097,"pro":false,"liveurl":"https:\/\/wopb.wpxpo.com\/design\/button-group-style-1\/","search":"","image":"https:\/\/wopb.wpxpo.com\/wp-content\/uploads\/2023\/08\/Button-1.jpg","hit":49,"category":[{"name":"Button Group","slug":"button-group"}]},{"name":"Product Slider #1 \u2013 Preset Design 9","ID":1898,"pro":false,"liveurl":"https:\/\/wopb.wpxpo.com\/design\/product-slider-1-preset-design-9\/","search":"","image":"https:\/\/wopb.wpxpo.com\/wp-content\/uploads\/2023\/08\/Product-Slider-1-\u2013-Preset-Design-9.jpg","hit":139,"category":[{"name":"Product slider","slug":"product-slider"}]},{"name":"Product Slider #1 \u2013 Preset Design 8","ID":1899,"pro":false,"liveurl":"https:\/\/wopb.wpxpo.com\/design\/product-slider-1-preset-design-8\/","search":"","image":"https:\/\/wopb.wpxpo.com\/wp-content\/uploads\/2023\/08\/Product-Slider-1-\u2013-Preset-Design-5.jpg","hit":98,"category":[{"name":"Product slider","slug":"product-slider"}]},{"name":"Product Slider #1 \u2013 Preset Design 7","ID":1900,"pro":false,"liveurl":"https:\/\/wopb.wpxpo.com\/design\/product-slider-1-preset-design-7\/","search":"","image":"https:\/\/wopb.wpxpo.com\/wp-content\/uploads\/2023\/08\/Product-Slider-1-\u2013-Preset-Design-6.jpg","hit":101,"category":[{"name":"Product slider","slug":"product-slider"}]},{"name":"Product Slider #1 \u2013 Preset Design 6","ID":1901,"pro":false,"liveurl":"https:\/\/wopb.wpxpo.com\/design\/product-slider-1-preset-design-6\/","search":"","image":"https:\/\/wopb.wpxpo.com\/wp-content\/uploads\/2023\/08\/Product-Slider-1-\u2013-Preset-Design-7.jpg","hit":91,"category":[{"name":"Product slider","slug":"product-slider"}]},{"name":"Product Slider #1 \u2013 Preset Design 5","ID":1902,"pro":false,"liveurl":"https:\/\/wopb.wpxpo.com\/design\/product-slider-1-preset-design-5\/","search":"","image":"https:\/\/wopb.wpxpo.com\/wp-content\/uploads\/2023\/08\/Product-Slider-1-\u2013-Preset-Design-8.jpg","hit":192,"category":[{"name":"Product slider","slug":"product-slider"}]},{"name":"Product Slider #1 \u2013 Preset Design 4","ID":1897,"pro":false,"liveurl":"https:\/\/wopb.wpxpo.com\/design\/product-slider-1-preset-design-4\/","search":"","image":"https:\/\/wopb.wpxpo.com\/wp-content\/uploads\/2023\/08\/Product-Slider-1-\u2013-Preset-Design-4.jpg","hit":61,"category":[{"name":"Product slider","slug":"product-slider"}]},{"name":"Product Slider #1 \u2013 Preset Design 3","ID":1896,"pro":false,"liveurl":"https:\/\/wopb.wpxpo.com\/design\/product-slider-1-preset-design-3\/","search":"","image":"https:\/\/wopb.wpxpo.com\/wp-content\/uploads\/2023\/08\/Product-Slider-1-\u2013-Preset-Design-3.jpg","hit":117,"category":[{"name":"Product slider","slug":"product-slider"}]},{"name":"Product Slider #1 \u2013 Preset Design 2","ID":1894,"pro":false,"liveurl":"https:\/\/wopb.wpxpo.com\/design\/product-slider-1-preset-design-2\/","search":"","image":"https:\/\/wopb.wpxpo.com\/wp-content\/uploads\/2023\/08\/Product-Slider-1-\u2013-Preset-Design-2.jpg","hit":198,"category":[{"name":"Product slider","slug":"product-slider"}]},{"name":"Product Slider #1 \u2013 Preset Design 1","ID":1890,"pro":false,"liveurl":"https:\/\/wopb.wpxpo.com\/design\/product-slider-1-preset-design-1\/","search":"","image":"https:\/\/wopb.wpxpo.com\/wp-content\/uploads\/2023\/08\/Product-Slider-1-\u2013-Preset-Design-1.jpg","hit":213,"category":[{"name":"Product slider","slug":"product-slider"}]},{"name":"Product Search &#8211; Preset Design 6","ID":1856,"pro":true,"liveurl":"https:\/\/wopb.wpxpo.com\/design\/product-search1-preset-design-6\/","search":"","image":"https:\/\/wopb.wpxpo.com\/wp-content\/uploads\/2023\/05\/Product-search-image-6-min.png","hit":16,"category":[{"name":"Product Search","slug":"product-search"}]},{"name":"Product Search &#8211; Preset Design 5","ID":1671,"pro":true,"liveurl":"https:\/\/wopb.wpxpo.com\/design\/product-search-1-preset-design-5\/","search":"","image":"https:\/\/wopb.wpxpo.com\/wp-content\/uploads\/2023\/05\/Product-search-image-5-min.png","hit":23,"category":[{"name":"Product Search","slug":"product-search"}]},{"name":"Product Search &#8211; Preset Design 4","ID":1670,"pro":true,"liveurl":"https:\/\/wopb.wpxpo.com\/design\/product-search-1-preset-design-4\/","search":"","image":"https:\/\/wopb.wpxpo.com\/wp-content\/uploads\/2023\/05\/Product-search-image-4.png","hit":36,"category":[{"name":"Product Search","slug":"product-search"}]},{"name":"Product Search &#8211; Preset Design 3","ID":1669,"pro":true,"liveurl":"https:\/\/wopb.wpxpo.com\/design\/product-search-1-preset-design-3\/","search":"","image":"https:\/\/wopb.wpxpo.com\/wp-content\/uploads\/2023\/05\/Product-search-image-3-min.png","hit":25,"category":[{"name":"Product Search","slug":"product-search"}]},{"name":"Product Search &#8211; Preset Design 2","ID":1668,"pro":true,"liveurl":"https:\/\/wopb.wpxpo.com\/design\/product-search-1-preset-design-2\/","search":"","image":"https:\/\/wopb.wpxpo.com\/wp-content\/uploads\/2023\/05\/Product-search-image-2-min.png","hit":26,"category":[{"name":"Product Search","slug":"product-search"}]},{"name":"Product Search &#8211; Preset Design 1","ID":1664,"pro":true,"liveurl":"https:\/\/wopb.wpxpo.com\/design\/product-search-1-preset-design-1\/","search":"","image":"https:\/\/wopb.wpxpo.com\/wp-content\/uploads\/2023\/05\/Product-search-image-1-min.png","hit":29,"category":[{"name":"Product Search","slug":"product-search"}]},{"name":"Product Category #3 \u2013 Preset Design 1","ID":1618,"pro":true,"liveurl":"https:\/\/wopb.wpxpo.com\/design\/product-category-3-preset-design-1\/","search":"","image":"https:\/\/wopb.wpxpo.com\/wp-content\/uploads\/2023\/01\/v1.jpg","hit":64,"category":[{"name":"Product Category 3","slug":"product-category-3"}]},{"name":"Product Grid #4 &#8211; Preset Design 5","ID":697,"pro":true,"liveurl":"https:\/\/wopb.wpxpo.com\/design\/preset-design-5-3\/","search":"","image":"https:\/\/wopb.wpxpo.com\/wp-content\/uploads\/2021\/03\/pg4_design_5.jpg","hit":267,"category":[{"name":"Product Grid 4","slug":"product-grid-4"}]},{"name":"Product Grid #4 &#8211; Preset Design 3","ID":695,"pro":true,"liveurl":"https:\/\/wopb.wpxpo.com\/design\/preset-design-3-6\/","search":"","image":"https:\/\/wopb.wpxpo.com\/wp-content\/uploads\/2021\/03\/pg4_design_3.jpg","hit":160,"category":[{"name":"Product Grid 4","slug":"product-grid-4"}]},{"name":"Product Grid #4 &#8211; Preset Design 2","ID":694,"pro":true,"liveurl":"https:\/\/wopb.wpxpo.com\/design\/preset-design-2-7\/","search":"","image":"https:\/\/wopb.wpxpo.com\/wp-content\/uploads\/2021\/03\/pg4_design_2.jpg","hit":228,"category":[{"name":"Product Grid 4","slug":"product-grid-4"}]},{"name":"Product Grid #4 &#8211; Default Preset Design","ID":693,"pro":false,"liveurl":"https:\/\/wopb.wpxpo.com\/design\/default-preset-design-7\/","search":"","image":"https:\/\/wopb.wpxpo.com\/wp-content\/uploads\/2021\/03\/pg4_design_1.jpg","hit":1724,"category":[{"name":"Product Grid 4","slug":"product-grid-4"}]},{"name":"Product Grid #4 &#8211; Preset Design 4","ID":696,"pro":true,"liveurl":"https:\/\/wopb.wpxpo.com\/design\/preset-design-4\/","search":"","image":"https:\/\/wopb.wpxpo.com\/wp-content\/uploads\/2021\/03\/pg4_design_4.jpg","hit":148,"category":[{"name":"Product Grid 4","slug":"product-grid-4"}]},{"name":"Product Grid #1 &#8211; Default Variation","ID":474,"pro":false,"liveurl":"https:\/\/wopb.wpxpo.com\/design\/product-grid-1-default-variation\/","search":"","image":"https:\/\/wopb.wpxpo.com\/wp-content\/uploads\/2020\/10\/Product-Grid-1-Variation-01.jpg","hit":2896,"category":[{"name":"Product Grid 1","slug":"product-grid-1"}]},{"name":"Product Grid #1 &#8211; Variation 2","ID":475,"pro":false,"liveurl":"https:\/\/wopb.wpxpo.com\/design\/preset-design-2-2\/","search":"","image":"https:\/\/wopb.wpxpo.com\/wp-content\/uploads\/2020\/10\/pg1_design_2.jpg","hit":1931,"category":[{"name":"Product Grid 1","slug":"product-grid-1"}]},{"name":"Product Grid #1 &#8211; Variation 3","ID":476,"pro":false,"liveurl":"https:\/\/wopb.wpxpo.com\/design\/preset-design-3-2\/","search":"","image":"https:\/\/wopb.wpxpo.com\/wp-content\/uploads\/2020\/10\/Product-Grid-1-Variation-03.jpg","hit":1409,"category":[{"name":"Product Grid 1","slug":"product-grid-1"}]},{"name":"Product Grid #1 &#8211; Variation 4","ID":477,"pro":false,"liveurl":"https:\/\/wopb.wpxpo.com\/design\/variation-4\/","search":"","image":"https:\/\/wopb.wpxpo.com\/wp-content\/uploads\/2020\/10\/Product-Grid-1-Variation-04.jpg","hit":1235,"category":[{"name":"Product Grid 1","slug":"product-grid-1"}]},{"name":"Product Grid #1 &#8211; Variation 5","ID":478,"pro":false,"liveurl":"https:\/\/wopb.wpxpo.com\/design\/variation-5\/","search":"","image":"https:\/\/wopb.wpxpo.com\/wp-content\/uploads\/2020\/10\/Product-Grid-1-Variation-05.jpg","hit":1371,"category":[{"name":"Product Grid 1","slug":"product-grid-1"}]}]